{
    "id": "KLM0002",
    "name": "Baagu",
    "gender": "M",
    "location_details": "Girikula, Kirigal Ebe Road, Kiripokuna Road, Diwulpallama Road, Bagure, Palukotawala, Aliya Wala, Kudaram Gala, Bagure \u2013 Godagedipokuna Rd, Diwulpallama wewa, Okanda Wela, Park Entrance, Orukema Plains, Helawa",
    "correlation_details": "Observed mating with KLF0008\nObserved mating with KLF0006\nObserved mating with KLF0022\nObserved together with KLF0038\nObserved fighting with KLM0029",
    "image_path_list": [
        "images/KLM0002/image_1.jpeg",
        "images/KLM0002/image_2.jpeg",
        "images/KLM0002/image_3.jpeg"
    ],
    "zone_list": [
        "A",
        "C"
    ],
    "date_first_seen": "2018-07-24",
    "date_last_seen": "2025-04-24",
    "mother_id": ""
}